setup.py
lyd_demo/__init__.py
lyd_demo/calc.py
lyd_demo.egg-info/PKG-INFO
lyd_demo.egg-info/SOURCES.txt
lyd_demo.egg-info/dependency_links.txt
lyd_demo.egg-info/top_level.txt
lyd_demo.egg-info/zip-safe
lyd_demo/sub_package/__init__.py
lyd_demo/sub_package/show.py